opendbc/__init__.py
opendbc/can/__init__.py
opendbc/can/can_define.py
opendbc/can/packer.py
opendbc/can/parser.py
opendbc/can/tests/__init__.py
opendbc/can/tests/test_checksums.py
opendbc/can/tests/test_dbc_exceptions.py
opendbc/can/tests/test_dbc_parser.py
opendbc/can/tests/test_define.py
opendbc/can/tests/test_packer_parser.py
opendbc/can/tests/test_parser_performance.py
opendbc/dbc/__init__.py
opendbc/dbc/generator/generator.py
opendbc/dbc/generator/test_generator.py
opendbc/dbc/generator/chrysler/_stellantis_common_ram.py
opendbc/dbc/generator/hyundai/hyundai_kia_mando_corner_radar.py
opendbc/dbc/generator/hyundai/hyundai_kia_mando_front_radar.py
opendbc/dbc/generator/tesla/radar_common.py
opendbc/dbc/generator/tesla/tesla_radar_bosch.py
opendbc/dbc/generator/tesla/tesla_radar_continental.py
opendbc-0.1.0.dist-info/LICENSE
opendbc-0.1.0.dist-info/METADATA
opendbc-0.1.0.dist-info/WHEEL
opendbc-0.1.0.dist-info/top_level.txt
opendbc-0.1.0.dist-info/RECORD
