Metadata-Version: 2.1
Name: opendbc
Version: 0.1.0
Summary: CAN bus databases and tools (pre-release)
Author-email: Vehicle Researcher <user@comma.ai>
License: Copyright (c) 2020, Comma.ai, Inc.
Project-URL: homepage, https://github.com/commaai/opendbc
Requires-Python: >=3.9
License-File: LICENSE
